README.md
setup.py
avalares/__init__.py
avalares/__main__.py
avalares/parser.py
avalares/pattern_detector.py
avalares/utils.py
avalares.egg-info/PKG-INFO
avalares.egg-info/SOURCES.txt
avalares.egg-info/dependency_links.txt
avalares.egg-info/entry_points.txt
avalares.egg-info/top_level.txt