Metadata-Version: 1.1
Name: avalares
Version: 0.1.2
Summary: Automatic text data extraction tool
Home-page: https://github.com/matthewscholefield/avalares
Author: Matthew D. Scholefield
Author-email: matthew331199@gmail.com
License: UNKNOWN
Keywords: avalares
Platform: UNKNOWN
Classifier: Development Status :: 3 - Alpha
Classifier: Intended Audience :: Developers
Classifier: Programming Language :: Python :: 3
Classifier: Programming Language :: Python :: 3.4
Classifier: Programming Language :: Python :: 3.5
Classifier: Programming Language :: Python :: 3.6
